modules/__init__.py
modules/audio.py
modules/base.py
modules/image.py
modules/text.py
modules/video.py
neyro_library-0.2.0.dist-info/LICENSE
neyro_library-0.2.0.dist-info/METADATA
neyro_library-0.2.0.dist-info/WHEEL
neyro_library-0.2.0.dist-info/top_level.txt
neyro_library-0.2.0.dist-info/RECORD
