Metadata-Version: 2.1
Name: neyro-library
Version: 0.2.0
Summary: Library for interacting with NeyroAPI
Author: Chelik23
Author-email: workghmail5775@gmail.com
Classifier: Programming Language :: Python :: 3
Classifier: License :: OSI Approved :: Apache Software License
Classifier: Operating System :: OS Independent
Requires-Python: >=3.11
License-File: LICENSE
Requires-Dist: requests
Requires-Dist: eventlet
Requires-Dist: pyee
